hiyobot/__init__.py
hiyobot/hc-wait4inp.test.py
hiyobot/zhc-wait4inp.test.py
hiyobot/hackchat/__init__.py
hiyobot/zhangchat/__init__.py
hiyobot-0.2.7.dist-info/LICENSE
hiyobot-0.2.7.dist-info/METADATA
hiyobot-0.2.7.dist-info/WHEEL
hiyobot-0.2.7.dist-info/top_level.txt
hiyobot-0.2.7.dist-info/RECORD
