Metadata-Version: 2.1
Name: hiyobot
Version: 0.2.7
Summary: A simple bot framework for Hack.chat.
Home-page: https://github.com/Hiyoteam/hiyobot
Author: MaggieLOL
Author-email: tanhanzesnd@gmail.com
License: GPL-2.0
Keywords: bot hack.chat hack.chat-bot
Classifier: Development Status :: 3 - Alpha
Classifier: Intended Audience :: Developers
Classifier: Topic :: Software Development :: Libraries :: Python Modules
Classifier: Programming Language :: Python :: 3
Classifier: Programming Language :: Python :: 3.10
License-File: LICENSE
Requires-Dist: cffi (==1.15.1)
Requires-Dist: gevent (==22.10.2)
Requires-Dist: greenlet (==2.0.2)
Requires-Dist: pycparser (==2.21)
Requires-Dist: websocket-client
Requires-Dist: zope.event (==4.6)
Requires-Dist: zope.interface (==6.0)
